slurmlint/__init__.py
slurmlint/__version__.py
slurmlint/cli.py
slurmlint/hosts.py
slurmlint/linter.py
slurmlint-0.0.3.dist-info/LICENSE
slurmlint-0.0.3.dist-info/METADATA
slurmlint-0.0.3.dist-info/WHEEL
slurmlint-0.0.3.dist-info/entry_points.txt
slurmlint-0.0.3.dist-info/top_level.txt
slurmlint-0.0.3.dist-info/RECORD
